crycompare/__init__.py
crycompare/history.py
crycompare/price.py
crycompare/social.py
crycompare-1.2.1.dist-info/METADATA
crycompare-1.2.1.dist-info/RECORD
crycompare-1.2.1.dist-info/WHEEL
crycompare-1.2.1.dist-info/top_level.txt
