Metadata-Version: 2.1
Name: crycompare
Version: 1.2.1
Summary: Python wrapper for CryptoCompare public API
Home-page: https://github.com/stefs304/cryCompare
Author: Stefan Stojanovic
Author-email: stefs304@gmail.com
License: UNKNOWN
Platform: UNKNOWN
Classifier: Programming Language :: Python :: 3
Classifier: Programming Language :: Python :: 2
Classifier: License :: OSI Approved :: MIT License
Classifier: Operating System :: OS Independent
Requires-Dist: requests
